CaozuoxitongJiandanShixianYuJibenyuanli/README.md
CaozuoxitongJiandanShixianYuJibenyuanli/__init__.py
CaozuoxitongJiandanShixianYuJibenyuanli/__main__.py
CaozuoxitongJiandanShixianYuJibenyuanli/file.epub
CaozuoxitongJiandanShixianYuJibenyuanli/index.html
CaozuoxitongJiandanShixianYuJibenyuanli/css/__init__.py
CaozuoxitongJiandanShixianYuJibenyuanli/css/annotations.css
CaozuoxitongJiandanShixianYuJibenyuanli/css/main.css
CaozuoxitongJiandanShixianYuJibenyuanli/css/normalize.css
CaozuoxitongJiandanShixianYuJibenyuanli/css/popup.css
CaozuoxitongJiandanShixianYuJibenyuanli/font/__init__.py
CaozuoxitongJiandanShixianYuJibenyuanli/font/fontello.eot
CaozuoxitongJiandanShixianYuJibenyuanli/font/fontello.svg
CaozuoxitongJiandanShixianYuJibenyuanli/font/fontello.ttf
CaozuoxitongJiandanShixianYuJibenyuanli/font/fontello.woff
CaozuoxitongJiandanShixianYuJibenyuanli/img/__init__.py
CaozuoxitongJiandanShixianYuJibenyuanli/img/annotator-glyph-sprite.png
CaozuoxitongJiandanShixianYuJibenyuanli/img/annotator-icon-sprite.png
CaozuoxitongJiandanShixianYuJibenyuanli/img/apple-touch-icon.png
CaozuoxitongJiandanShixianYuJibenyuanli/img/cancelfullscreen.png
CaozuoxitongJiandanShixianYuJibenyuanli/img/close.png
CaozuoxitongJiandanShixianYuJibenyuanli/img/fullscreen.png
CaozuoxitongJiandanShixianYuJibenyuanli/img/loader.gif
CaozuoxitongJiandanShixianYuJibenyuanli/img/menu-icon.png
CaozuoxitongJiandanShixianYuJibenyuanli/img/save.png
CaozuoxitongJiandanShixianYuJibenyuanli/img/saved.png
CaozuoxitongJiandanShixianYuJibenyuanli/img/settings-s.png
CaozuoxitongJiandanShixianYuJibenyuanli/img/settings.png
CaozuoxitongJiandanShixianYuJibenyuanli/img/star.png
CaozuoxitongJiandanShixianYuJibenyuanli/js/__init__.py
CaozuoxitongJiandanShixianYuJibenyuanli/js/epub.js
CaozuoxitongJiandanShixianYuJibenyuanli/js/epub.min.js
CaozuoxitongJiandanShixianYuJibenyuanli/js/epub.min.map
CaozuoxitongJiandanShixianYuJibenyuanli/js/hooks.min.js
CaozuoxitongJiandanShixianYuJibenyuanli/js/hooks.min.map
caozuoxitong_jiandan_shixian_yu_jibenyuanli-2024.3.4.0.dist-info/METADATA
caozuoxitong_jiandan_shixian_yu_jibenyuanli-2024.3.4.0.dist-info/WHEEL
caozuoxitong_jiandan_shixian_yu_jibenyuanli-2024.3.4.0.dist-info/entry_points.txt
caozuoxitong_jiandan_shixian_yu_jibenyuanli-2024.3.4.0.dist-info/top_level.txt
caozuoxitong_jiandan_shixian_yu_jibenyuanli-2024.3.4.0.dist-info/RECORD
